{
  "actions": [
    {
      "type": "createTable",
      "createTable": {
        "name": "purchase_status_response",
        "dartName": "PurchaseStatusResponse",
        "module": "test_server",
        "schema": "public",
        "columns": [
          {
            "name": "id",
            "columnType": 6,
            "isNullable": false,
            "columnDefault": "nextval('purchase_status_response_id_seq'::regclass)",
            "dartType": "int?"
          },
          {
            "name": "hasPurchased",
            "columnType": 1,
            "isNullable": false,
            "dartType": "bool"
          },
          {
            "name": "canPurchaseAgain",
            "columnType": 1,
            "isNullable": false,
            "dartType": "bool"
          },
          {
            "name": "isPrintingPending",
            "columnType": 1,
            "isNullable": false,
            "dartType": "bool"
          },
          {
            "name": "lastPurchaseDate",
            "columnType": 4,
            "isNullable": true,
            "dartType": "DateTime?"
          },
          {
            "name": "ticketId",
            "columnType": 6,
            "isNullable": true,
            "dartType": "int?"
          },
          {
            "name": "qrCodeData",
            "columnType": 0,
            "isNullable": true,
            "dartType": "String?"
          }
        ],
        "foreignKeys": [],
        "indexes": [
          {
            "indexName": "purchase_status_response_pkey",
            "elements": [
              {
                "type": 0,
                "definition": "id"
              }
            ],
            "type": "btree",
            "isUnique": true,
            "isPrimary": true
          }
        ],
        "managed": true
      }
    }
  ],
  "warnings": [],
  "migrationApiVersion": 1
}